caserec/__init__.py
caserec/clustering/__init__.py
caserec/clustering/kmedoids.py
caserec/clustering/paco.py
caserec/evaluation/__init__.py
caserec/evaluation/base_evaluation.py
caserec/evaluation/item_recomendation_functions.py
caserec/evaluation/item_recommendation.py
caserec/evaluation/rating_prediction.py
caserec/evaluation/statistical_analysis.py
caserec/recommenders/__init__.py
caserec/recommenders/item_recommendation/__init__.py
caserec/recommenders/item_recommendation/base_item_recommendation.py
caserec/recommenders/item_recommendation/bprmf.py
caserec/recommenders/item_recommendation/content_based.py
caserec/recommenders/item_recommendation/ensemble_average.py
caserec/recommenders/item_recommendation/ensemble_bpr.py
caserec/recommenders/item_recommendation/group_based_recommender.py
caserec/recommenders/item_recommendation/item_attribute_knn.py
caserec/recommenders/item_recommendation/itemknn.py
caserec/recommenders/item_recommendation/most_popular.py
caserec/recommenders/item_recommendation/paco_recommender.py
caserec/recommenders/item_recommendation/random_rec.py
caserec/recommenders/item_recommendation/user_attribute_knn.py
caserec/recommenders/item_recommendation/userknn.py
caserec/recommenders/rating_prediction/__init__.py
caserec/recommenders/rating_prediction/base_knn.py
caserec/recommenders/rating_prediction/base_nsvd1.py
caserec/recommenders/rating_prediction/base_rating_prediction.py
caserec/recommenders/rating_prediction/corec.py
caserec/recommenders/rating_prediction/gsvdplusplus.py
caserec/recommenders/rating_prediction/item_attribute_knn.py
caserec/recommenders/rating_prediction/item_msmf.py
caserec/recommenders/rating_prediction/item_nsvd1.py
caserec/recommenders/rating_prediction/itemknn.py
caserec/recommenders/rating_prediction/matrixfactorization.py
caserec/recommenders/rating_prediction/most_popular.py
caserec/recommenders/rating_prediction/nnmf.py
caserec/recommenders/rating_prediction/random_rec.py
CaseRecommender-1.1.1.dist-info/COPYING
CaseRecommender-1.1.1.dist-info/METADATA
CaseRecommender-1.1.1.dist-info/WHEEL
CaseRecommender-1.1.1.dist-info/top_level.txt
CaseRecommender-1.1.1.dist-info/RECORD
