Metadata-Version: 2.1
Name: CaseRecommender
Version: 1.1.1
Summary: A recommender systems framework for Python
Home-page: https://github.com/caserec/CaseRecommender
Author: Arthur Fortes <fortes.arthur@gmail.com>
Author-email: fortes.arthur@gmail.com
License: MIT License
Download-URL: https://github.com/caserec/CaseRecommender/archive/master.zip
Keywords: recommender systems,framework,collaborative filtering,content-based filtering,recommendation
Platform: UNKNOWN
Classifier: Intended Audience :: Developers
Classifier: Topic :: Software Development :: Build Tools
Classifier: License :: OSI Approved :: MIT License
Classifier: Programming Language :: Python :: 3
Classifier: Programming Language :: Python :: 3.4
Classifier: Programming Language :: Python :: 3.5
Classifier: Programming Language :: Python :: 3.6
Classifier: Intended Audience :: Developers
Classifier: Topic :: Software Development :: Build Tools
License-File: COPYING
Requires-Dist: numpy
Requires-Dist: scipy
Requires-Dist: scikit-learn
Requires-Dist: pandas
